[
  {
    "title": "Original Game Developer",
    "description": "Great game creator.",
    "members": [
      "Auxbrain Inc."
    ]
  },
  {
    "title": "Developer",
    "description": "They created this site.",
    "members": [
      "mikit"
    ]
  },
  {
    "title": "Technical Advisor",
    "description": "This service and the wasmegg suite share data bidirectionally via an API.",
    "members": [
      "mk2"
    ]
  },
  {
    "title": "Tester",
    "description": "They helped us with bug reports.",
    "members": [
      "members of Z's private coop channel",
      "Samthi99"
    ]
  },
  {
    "title": "Data Contributor",
    "description": "They contributed their game data for science. Without their cooperation, some statistical analyses would not have been possible.",
    "members": [
      "DhrMekmek",
      "MegadangerNo.1",
      "LimesLimesLimes",
      "DataCabbit",
      "TimelordSnowy",
      "Wargraymon 5",
      "liquoriceWB",
      "BoomTetris4Jeff",
      "Marblexake",
      "U.P. Yoars",
      "mrflîp",
      "EthanWilko",
      "PatMyDog",
      "ReactiveTopaz",
      "DrummerNeptune",
      "Smile4Miles2",
      "MisguidedMoose5982",
      "Andreas6295",
      "xStarlordx2",
      "shuvoshuvo629",
      "wood_420",
      "AsteriaHershey",
      "FluffyBunnie204",
      "mtgeekman",
      "WyntersFyre67",
      "MavoBlavo",
      "Jamesh9000",
      "AccreditedFrenemy12",
      ":..Kelsie..:",
      ":-(r*14)-:",
      "klusark",
      "ks14049282",
      "srawratsmc",
      "xJehu",
      "Zacuna",
      "fuzzy2tuw",
      "VideoGameDeveloper",
      "AManCannotRap",
      "Elvarg",
      "Intrepidexplorer743",
      "TheMagnusCarlsen (SLC)",
      "Stealthii",
      "emilyadawi",
      "DangerMcStranger",
      "dnelson597",
      "LazyBrokerAz",
      "GrumpyMum27",
      "Cranrnan1",
      "akroh",
      "Hiram Is Tyred",
      "AesisX",
      "",
      "Therbear17",
      "PrincePretty123",
      "Damachaman",
      "vorskin",
      "Labersin",
      "UnambiguousFort",
      "BlackBullet1504",
      "Szute",
      "drureder",
      "mvb123456",
      "tillertms",
      "Blue0Haze",
      "Bellowing Unicorn 433",
      "BlwAvg",
      "",
      "ry22637",
      "eragon003326",
      "Crafter0800",
      "odie714",
      "lnternaIScreaming",
      "Th3AnT0in3",
      "Sepatown",
      "prengles",
      "FordAplawz",
      "NettlesomeCricket42",
      "Allegria84",
      "RaviEdho",
      "dream8xq",
      "zukesnsloots",
      "CasualGamer!",
      "mrisj",
      "Ipak123",
      "cur.by",
      "VagabondShip55081",
      "SupremeEdgelord",
      "TC Foxtaur",
      "Favst89",
      "DastardlyJaguar22555",
      "Marzigma",
      "1LC6030",
      "EffectiveMess",
      "Cobracrystal3141",
      "Brad164",
      "Sabbors",
      "AuraSix",
      "zach.sfield",
      "cyrious15",
      "",
      "Puma8u2",
      "LadyKojac",
      "lekreb31",
      "CabbageShart",
      "MOSSMANIA",
      "JackfockinShephard",
      "bobbert021",
      "CosmicMagic421",
      "Stormin91",
      "likeDream",
      "calvin1719",
      "antuvschle",
      "melatoninlol",
      "RedheadedJock1723",
      "Venomejb",
      "jeffcsx",
      "Gleeok",
      "synthparadox",
      "Domokuncheckmate",
      "12BarBluesBr",
      "ergeen9",
      "Zag1310",
      "AtavisticBeast71771",
      "PristinePrincess16",
      "CdrSnuggles",
      "lapinozz",
      "Lorinefairy",
      "PerfectGremlin2051",
      "OvidiuC",
      "Meyerditch",
      "Zælius",
      "Scowler76",
      "ThomasAudenaert",
      "JTibb",
      "Pellosaurus",
      "TentaBox",
      "ellipsis999",
      "justlac",
      "mattmb223",
      "john_9468",
      "Darth Flip",
      "DaFabNam",
      "ShdwWlkr",
      "CarpetSage",
      "Trollweryne",
      "Tyler_Newton",
      "WiNoJoE",
      "RandomGuy_1",
      "Laverne11",
      "uglyandsingle",
      "whereami8224",
      "KulM96",
      "Aesthetic Wraith 306",
      "Auborop",
      "lyradog",
      "jfriedly",
      "Jon 2003 south",
      "ÁngelPiret",
      "Brubber1",
      "hatgrab",
      "ArcticGamer90",
      "flash9387",
      "BoomTetris4Jonas",
      "THINGMAJIG-1",
      "BlatantDisguise",
      "M4disonc21",
      "Fierce Lizard of Blue Cave",
      "Zeiram00X",
      "Flaedrian",
      "sgebrial",
      "BloviatingCop256",
      "kb95",
      "Chamorro303",
      "Portentum",
      "freezin11",
      "Burarutal",
      "doctorblah",
      "NemoHose",
      "CynosureMasterDragon",
      "MercifulCritter404",
      "Kylian272",
      "humter_",
      "Snapo90",
      "Farmboy242424",
      "PandoraNox",
      "wdoe717",
      "-(ZombiePig)-",
      "Bobberino69420",
      "Flyingplankton",
      "Alechien",
      "Jawuray",
      "durppie1",
      "AllikazamOG",
      "ZespTheKraken",
      "kreon24",
      "tug4fire",
      "SassySalvador",
      "PhunkMaster",
      "sora912194",
      "humbleColumn",
      "Guinnberg",
      "tahw4228",
      "Yabadabadoo￼",
      "SomeDaveGuy",
      "JustGary9999",
      "ZoomStreak",
      "Agoo Matt",
      "Trekkie_Cow124",
      "trlta",
      "skeetyeet4795",
      "Wh1skeysix",
      "AdDoBe",
      "Kazimir1234",
      "xXZeus82Xx",
      "SnowStorm the cat",
      "MrOrange9000",
      "Epicinfiniti999",
      "TheSmeggyBean6000",
      "Stipling",
      "griffinwood",
      "ARC_AJS",
      "dambitme1023",
      "LordBaconBane",
      "birdlawn",
      "Kihan1234",
      "GeorgeSmiley63",
      "Lacrim05a",
      "ProspectPat",
      "cosmickalamity",
      "Candygnome",
      "ChronicHippy771",
      "MightyMouse4436",
      "007SplendidWizard",
      "itcouldbeaballoon",
      "CoffeeKitsune98",
      "KingJohnOeuf",
      "JTPF",
      "Finalizer804",
      "jdoogie",
      "scottyy414",
      "petrolsmellsbad",
      "riknata",
      "maplessyrupss",
      "Cardodd",
      "FasTerv",
      "M3hni",
      "*!(frrtt)!",
      "Pokepokeye",
      "Rafvk",
      "xMrPoi",
      "TripleDose",
      "Alaefin Kentaris",
      "jlyons264",
      "ianellwood",
      "dangitDepa",
      "luismh1000",
      "spine13",
      "Brozono",
      "Orycheon",
      "Hereisdan",
      "Dell The Angry Soldier",
      "wh1tec4tblack",
      "kaankrncom",
      "Ilmorgi88",
      "amazethisrabble",
      "Wherdgo",
      "adam00se",
      "DisorderedLattice",
      "az_reth",
      "Alien4337",
      "WhaiFuji",
      "Brookelyn<:)",
      "Mr_Grae",
      "subbu21c",
      "StrayManatee703",
      "MQ Inc",
      "+lainsan+",
      "Stinky Monkey Poopie Pants",
      "mossyking",
      "lacrimans",
      "EpKolhd",
      "MechanicalMedic93628",
      "Matta9246",
      "BadBogeyman82915",
      "BlueDog2005",
      "Wavetune",
      "IIAsperatisII",
      "Decko🙃",
      "getcarld",
      "Alexandar K.",
      "Katant",
      "NappingBird93718",
      "Snowbo8p",
      "consumeDrywall",
      "Fireruff",
      "jojonala",
      "Dark Cultivator 200",
      "thedaffy1977",
      "rhapsodiac",
      "EditorialMonopoly21",
      "PinkJalapeno37979",
      "SarsFunfEins",
      "E-Ray🦖",
      "Tommy52ᴼᵀᵀᴱᴿ",
      "elHobo5",
      "panamintinus",
      "Khrysaoros",
      "MagiCarpets",
      "LunarPug56376",
      "Wazaouille",
      "GreenzQe",
      "Alpiicek",
      "NinjaDome",
      "redshadow1297",
      "Eggonairre",
      "dmsherry",
      "Soviet Shrimp",
      "not lord",
      "TurtleTamer",
      "zadaBoss",
      "NomadTheCreator",
      "joeswanson",
      "Krisman",
      "St:An",
      "Ineffable Conjourer 780",
      "Tamfire96",
      "SuperFastSloth420",
      "CelesteP03",
      "SirEggbertDerply",
      "Brilliant Bee 402",
      "ChrisRdontplayhorse",
      "sassskatt",
      "mokenut",
      "bhq.mikal",
      "AzzhStrike",
      "Knexoos",
      "Saturn_ity",
      "sacinici",
      "Sarkahan",
      "VioletLion888",
      "typicalchick3n",
      "wina.189",
      "Calcaneus8",
      "Jak0p",
      "AsianNation271",
      "Sdz169",
      "TheNamesRocky",
      "SPCOxion",
      "Dazai Gamer",
      "HypotheticalVase",
      "MissConstrue",
      "melissaedow",
      "tuba_king",
      "Claire00x",
      "HamR139",
      "OmegaWolf2704",
      "The KGBeast",
      "vrp36",
      "Andi Schulz",
      "TheIpodk9",
      "EvilWabbit7",
      "JB0221",
      "potatocat06",
      "fishyvishy123",
      "NerdyDingo345",
      "SatiricalPotential27",
      "merculid",
      "dwk5074",
      "Lazzattttt",
      "BertexAltivium",
      "FireLordRufio",
      "GDCytosine",
      "Anubis Khan",
      "di3go1985",
      "NoninhoX",
      "Chris✅",
      "cwspurple",
      "brendan63304",
      "PrincessLucid",
      "drubick",
      "NicF1985",
      "boscoliu3",
      "Freshyfresh666",
      "GoombaSteve",
      "SadisticNarwall",
      "datalyssa",
      "BooDog325",
      "nvhhr",
      "PointyBrawler14",
      "Shugy0",
      "Omegavoids",
      "GrizzlyNacho",
      "MrJspeed",
      "moconne11",
      "EnticingCanine",
      "wheatleyg",
      "Vectorman37",
      "Viewtifulma0",
      "RunceytheFireBird",
      "Jürgenwürgen",
      "magearna1",
      "vincentvaes",
      "Billguy2",
      "Goche2019",
      "HereBCPCdied",
      "Pugnata",
      "BiologicalFrame4",
      "Kaalgrah",
      "SaladiumForkus",
      "UndeadAssassin007",
      "iamarzan87",
      "DroningJalapeno374",
      "Ximo1205",
      "deneb55",
      "DogeBeOrNotDogeBe",
      "Everdell",
      "AmGumbo",
      "Basiayo",
      "Xandrez192",
      "Corn0nTheCobb",
      "');dropped--",
      "3qu1n0x",
      "theoriginalnoob",
      "Personifire",
      "Numerlor",
      "mushedxd",
      "AmberRhinoceros44428",
      "Zoooolino",
      "ThePeriii",
      "Pneumatus",
      "princessshushu2539",
      "Kirian42",
      "calvinpartdeux",
      "Jonawesome1991",
      "69PapiGrande69",
      "UnintelligibleEnt481",
      "MrMaijk",
      "Neldalf",
      "TheBubbaCat",
      "-KRSY-",
      "SydBarret1961",
      "dustinyo_",
      "Brave Pilot from Skinny Lake",
      "Pockets Perfected",
      "Mentalist761",
      "SpudOfDoom",
      "theFliris",
      "bêndev",
      "DarkLotus369",
      "LightMercenary4595",
      "Frank．。",
      "muhothecelestial",
      "saphire456213",
      "RomiressR",
      "Cliff :|",
      "fuzzy254",
      "JACKBATMAN32",
      "LoadedAlchemist2606",
      "Hax3lsrt",
      "~MirMir~",
      "najnajnajnajnaj",
      "xylofreak03",
      "Yonfirmed",
      "SlimeBuddy",
      "keenanjgm",
      "airt43",
      "PernicousD",
      "NixonInAJar",
      "_xirtic",
      "nvrgonnagiveyouup",
      "KosokuIkari",
      "Puzzled Dinosaur of the Glade",
      "Porkpenknife",
      "TentacledChef27946",
      "o_g .",
      "paperfrog23",
      "VedonRodd",
      "jpaoad31",
      "joshpancooking",
      "aetop",
      "PsychologicalSnack",
      "",
      "GlenCoco1384",
      "Kingflo1994",
      "afaust242",
      "ArdentLizard2101",
      "noodle-spoodle",
      "SUCRAM THE LEGEND",
      "wagerbomb",
      "abik101",
      "EitorSemH",
      "Soveliss42",
      "killzone699669",
      "tokemoi",
      "Blackguard666",
      "Mcilva The Orange Seeker",
      "GoldenProphet89503",
      "Soulcyon",
      "The11thDoctor2002",
      "The_Narrat0r",
      "jacobbrand07",
      "CrusaderX25",
      "AmiableAndroid",
      "Bobofats",
      "PersnicketyLord19346",
      "Cowman911",
      "sagudson",
      "Awolf5656",
      "Weebledorf",
      "MagneticTurkey",
      "guitalex",
      "HankelTransform",
      "",
      "Donpedrosky",
      "juscuz17",
      "afrefde",
      "louisgalvan",
      "HungrySinger120",
      "Pubert 69",
      "OatsOatmeal",
      "BobSki778",
      "WTFoxtrot20",
      "Destable",
      "Etneus95",
      "GatoEl93",
      "OutdoorProfit975",
      "Smile_4_Miles",
      "IridescentCrystal452",
      "🪴catsandplants1312",
      "Chkiken23",
      "Zenga01",
      "itzDahdee0417",
      "battler",
      "JPthesheepy",
      "twitchy1515",
      "Kirby9890",
      "Drsnipe0987",
      "WreckingGremlin76518",
      "Darknightx03",
      "Father Berman",
      "AccreditedLunatic477",
      "Glotfegers The Rebel",
      "Cheesestickle",
      "PepoThe",
      "SouthsideMilt",
      "noelgoo",
      "lalongspur",
      "kbuffington",
      "KKnudson23",
      "TextualTeller19",
      "Tombstone888",
      "cptbrucebatteringram",
      "InTehCorner",
      "! jamesoss117 !",
      "sk73828262815",
      "lassiedutch",
      "Pyrofessor42",
      "julietalphadelta",
      "NYYanksH8r",
      "Gøøgle",
      "WheatWhacker1",
      "MiscMe1",
      "joseocio192",
      "friedguppy",
      "Kranked_Original",
      "moofus2000",
      "stephanigilliam",
      "JonathanC 7",
      "nessiesson",
      "gbgopher",
      "opospi",
      "crazyjalapno",
      "",
      "Thijs10p",
      "Hubertzgl",
      "SkittlesAsaurusX",
      "JamesB123456790",
      "ItsAWildPerson",
      "sap3lo",
      "8Matrixbalu8",
      "mattbenai",
      "HitThisCreeper",
      "Cwilson 21",
      "Yhorzo",
      "av3rag3jo3",
      "soycharliente",
      "ChupaThingy27",
      "yaDunnGoofed",
      "jakemate977",
      "Lord Of The Shallots",
      "RareCricket1866",
      "MonMario",
      "iwdidw",
      "maciarc314",
      "Player3Th0mas",
      "deyter33",
      "Killerögue",
      "NickPapagiorgio",
      "Bosaap23",
      "tmthy.",
      "FireHOTvolCano",
      "StringyQuark",
      "GrubbyLoon111",
      "ddubbin",
      "Drewsome071218",
      "sac7439",
      "Chaseq42",
      "Cripple500",
      "euaki1002",
      "tanrockstan34",
      "NoobtownMcgee",
      "Alexyx",
      "infinite20strings16",
      "SushiSt4R",
      "Mcsizzle808",
      "Doritin1",
      "KillerEdward",
      "BooShadowGin",
      "DerpIsBetter",
      "D3C4YINGC0RPS3",
      "Divine Lord of Golden Town",
      "LB9001",
      "Futon Type R",
      "SpinTolk",
      "Geickolonian",
      "Cavani*50",
      "Humorous Giant of Shiny Meadow",
      "Riggenstimple",
      "StaticShark1617",
      "Arvulus",
      "Mongela",
      "FebOneCorp",
      "NEvana0003",
      "josethim",
      "LucidDictator25",
      "SmartGuy42",
      "BigT1916",
      "pandorum.exe",
      "SomeHugeGuy",
      "Bakken0",
      "TeyrCrimson",
      "thighs7",
      "jiminymacca",
      "Ribzlike",
      ":Rabz1:",
      "natecrch",
      "LividToastie",
      "Joackim92",
      "definitelynotpnx",
      "thechampion900000",
      "ZDubReal",
      "drobUWP",
      "NikaoSkotos",
      "gendalia",
      "UnpopularBulldog4065",
      "blue92fox",
      "SuperMcAwesomeface",
      "oBlazin",
      "Se4l_69",
      "DAZX",
      "[DrPeach]",
      "Sulroy",
      "T4Z3RB34M",
      "Flumperton",
      "NobleKnight12708",
      "WyntersFyre01",
      "deepblue1231",
      "epticalc",
      "NEAY0F",
      "xX_Parzival13_Xx",
      "MrDrRoscoe",
      "RobFaie2",
      "Noahguu!",
      "Lucky#1000",
      "MrWazzles",
      "TeufelHundenO311",
      "Humpty Dumpty 99",
      "meisZWFLZ21",
      "IrishSE",
      "Xtotdam",
      "jfreder421",
      "smyge",
      "auxi2000",
      "Madjarov",
      "Mochungus",
      "caykkk",
      "gqzeoztnrtj9y",
      "UbiquitousCelery",
      "Leole11",
      "dannyfannypack",
      "RTcharles410",
      "jjagsyhudhd",
      "Conductor Bobo",
      "Mhizzing",
      "SirDilbet",
      "Akobak",
      "NoseHolder",
      "sammybw1",
      "MedinaXero",
      "LMaster765",
      "matthTwo",
      "rclary",
      "FuriousPandaFST",
      "Yolotrolboy",
      "Vinnie927",
      "banaan1798",
      "QuickBogeyman52799",
      "bobbepartdeux",
      "Jeefra",
      "JoshuaTree93",
      "UnpopularDesert3",
      "DJCohenPlayzYT",
      "Jokertolyan",
      "KimQ7555",
      "fiashdance",
      "Bonanza00",
      "Julien ☢️",
      "federico9292",
      "SarahLafayette",
      ":Jay",
      "XxEtho26xX",
      "Ozymandias195",
      "",
      "GodFoIIower",
      "0wzo",
      "sgbench",
      "Bmac1359",
      "EarlHickey5",
      "FastRunningEggman",
      "scrublrd333",
      "ijfletch35",
      "Kade_B_1995",
      "ghoooo0000",
      "AttractiveGourmet198",
      "MDJ88Megaman",
      "lifanov",
      "ellygaytor",
      "niekze",
      "Bergepa",
      "xChives",
      "notyouraveragetwink",
      "deejayjoycee",
      "Newtube453",
      "mathematicalcoffee",
      "||hexion||",
      "Dogeronii",
      "Tkt0nny",
      "Jasperite01",
      "AcidGamin593",
      "SymbioticRhythm28",
      "DRD4114",
      "mennoo1996",
      "BamBamtheMan",
      "AlexandreMarcondes",
      "EggcellentGamer",
      "RogueHipster4059",
      "danibaie",
      "Subject_Eleven_",
      "tehellis",
      "thespeedyone88",
      "Taylorification",
      "SticklerMeeseex",
      "IvlivsDtal",
      "tbmatuka",
      "sendboostgetcarried",
      "bctisdale19",
      "W4nsl3Y",
      "MaroonMoth9734",
      "PewX1337",
      "strepito66",
      "thederpybot",
      "ddotton",
      "MayFlour83",
      "TK421BSOD",
      "gumcheese",
      "khysteria",
      "Zappypoo",
      "DaRealPizza6837",
      "Nathan907",
      "SolicitousFootnote22",
      "TheDanster_YT",
      "MCWarhammers",
      "kukurablik",
      "PerfectWanderer211",
      "LukasvanDee132",
      "DiamondzBack",
      "Travbv",
      "Cobhalla",
      "swingys",
      "ljbear",
      "kingofallcrumbs",
      "SirNimble",
      "broonsd",
      "shilo1 44",
      "Quaka1995",
      "Caffeine000",
      "iseki 1700",
      "popiol999",
      "apocalypsematt",
      "mangoskits",
      "QuixoticMartyr29",
      "Conniestitution",
      "",
      "Templehill4000",
      "adi2oo4",
      "Shodan101",
      "Demxnster",
      "Reinthx",
      "Matti_Gutt",
      "colepng",
      "Snoopy913",
      "hellostarfall",
      "waitesm",
      "conor lolz",
      "AboutLuck",
      "mulhamhelal",
      "Bluwviolet01",
      "Reggie13240",
      "RezzOLute",
      "Daavi-_",
      "Cories98",
      "Lolsporeguy",
      "hokeygnocchi",
      "Darganon",
      "HazelNutter10",
      "Prentii",
      "aprks",
      "arty6511",
      "Skinny Ergos",
      "Kazoeru8",
      "BuffMission688",
      "FreezingCoin213",
      "WifiWFB",
      "Alicexo22",
      "PizzaGuyJoey",
      "TheBadDoggyy",
      "Perpx",
      "EatMeat69420",
      "hweeat",
      "SuicidalSnack",
      "anja orison",
      "TheDisease87",
      "Snarkfish",
      "BoardMirror",
      "onereddragon1",
      "FutureGypsy",
      "MetallicWarden5354",
      "PotatoBearSMO3871",
      "Tains72",
      "Altair017",
      "Cianokias",
      "osmosis_O",
      "DamBer005931",
      "Snukette",
      "",
      "semet13",
      "Just Some Brown",
      "Kelenius",
      "SuperDuperMystic6354",
      "RoboCastGames",
      "Nan0gamer7",
      "pl1z",
      "CatostrophicCipher69",
      "420Kazzooit",
      "Lokomotywa",
      "kyay10",
      "ZupaGrzybowaaaaa",
      "biggocl123",
      "Abecbu",
      "s02mike",
      "Mattkins33",
      "aznandyc",
      "its_t0x1c",
      "SirFrankOfMan",
      "charcolepix",
      "TheCxnnor",
      "Andthebeatgoeson7",
      ".GrizzlyT.",
      "ioiozi",
      "dergrosehd",
      "owaway ju",
      "10morty",
      "Sporkidoo",
      "-spelter-",
      "KurkaJajek",
      "HersheltheHuman",
      "OrneryBeagle7337",
      "Galaad006",
      "SoulSlayer1",
      "Erinkidd01",
      "Bonitamer Brownek",
      "drewchi1",
      "LucianHub.",
      "cupirl",
      "Corfal",
      "SupremeDalek2002",
      "ChrisIronhawk",
      "CopperSquire2587",
      "TheMisguidedRaven",
      "Bystrlite81",
      "Angry Frog of Yellow City",
      "Lord Thuul",
      "ColinColon89",
      "RealImpendingDoom",
      "aMeeEc11",
      "616c616e",
      "AngryGopher157",
      "BRDZY",
      "TheSnowPeas",
      "Zruler6",
      "bestfweinds",
      "ThomasAudenaert",
      "Rhianite",
      "ExtremeDog96460",
      "Rainbow Paladin",
      "Xnohohsd",
      "DraftedSkeleton",
      "Leec0",
      "Kilserz",
      "Floflp",
      "mwhite14",
      "B1llyg0at88",
      "JuggsAddict14",
      "HPSAyyLmao",
      "jpigg",
      "Lundster",
      "AcquaII07",
      "jikerwa",
      "Onyx Elessedil",
      "IRKillRoy",
      "Tom The Tomatooo",
      "mickicoco",
      "FnigePython"
    ]
  }
]